Metadata-Version: 2.1
Name: cedisa_report
Version: 1.6.0
Author: Gustavo Gomes Dias
Author-email: gustavo.dias@cedisa.com.br
License-File: LICENSE.txt
